AUTHORS.rst
LICENSE
MANIFEST.in
README.rst
setup.py
pygithub3/__init__.py
pygithub3/exceptions.py
pygithub3/github.py
pygithub3/core/__init__.py
pygithub3/core/client.py
pygithub3/core/compat.py
pygithub3/core/errors.py
pygithub3/core/json/__init__.py
pygithub3/core/result/__init__.py
pygithub3/core/result/base.py
pygithub3/core/result/link.py
pygithub3/core/result/normal.py
pygithub3/core/result/smart.py
pygithub3/core/third_libs/__init__.py
pygithub3/core/third_libs/link_header.py
pygithub3/requests/__init__.py
pygithub3/requests/base.py
pygithub3/requests/events/__init__.py
pygithub3/requests/events/networks.py
pygithub3/requests/events/orgs.py
pygithub3/requests/events/repos.py
pygithub3/requests/events/users.py
pygithub3/requests/gists/__init__.py
pygithub3/requests/gists/comments.py
pygithub3/requests/git_data/__init__.py
pygithub3/requests/git_data/blobs.py
pygithub3/requests/git_data/commits.py
pygithub3/requests/git_data/references.py
pygithub3/requests/git_data/tags.py
pygithub3/requests/git_data/trees.py
pygithub3/requests/issues/__init__.py
pygithub3/requests/issues/comments.py
pygithub3/requests/issues/events.py
pygithub3/requests/issues/labels.py
pygithub3/requests/issues/milestones.py
pygithub3/requests/orgs/__init__.py
pygithub3/requests/orgs/members.py
pygithub3/requests/orgs/teams.py
pygithub3/requests/pull_requests/__init__.py
pygithub3/requests/pull_requests/comments.py
pygithub3/requests/repos/__init__.py
pygithub3/requests/repos/collaborators.py
pygithub3/requests/repos/commits.py
pygithub3/requests/repos/downloads.py
pygithub3/requests/repos/forks.py
pygithub3/requests/repos/hooks.py
pygithub3/requests/repos/keys.py
pygithub3/requests/repos/watchers.py
pygithub3/requests/users/__init__.py
pygithub3/requests/users/emails.py
pygithub3/requests/users/followers.py
pygithub3/requests/users/keys.py
pygithub3/resources/__init__.py
pygithub3/resources/base.py
pygithub3/resources/events.py
pygithub3/resources/gists.py
pygithub3/resources/git_data.py
pygithub33.egg-info/PKG-INFO
pygithub33.egg-info/SOURCES.txt
pygithub33.egg-info/dependency_links.txt
pygithub33.egg-info/requires.txt
pygithub33.egg-info/top_level.txt
